Workbook
Name Aporte: Planilha1!$D$16
Name Patrimonio: Planilha1!$D$19
Name qtd_anos: Planilha1!$D$17
Name Rendimento_carteira: Planilha1!$D$11
Name Salario: Planilha1!$D$10
Name Sugestao_investimento: Planilha1!$D$12
Name Taxa_mensal: Planilha1!$D$18

Sheet Planilha1
B9: Configurações
B10: Salário | D10: 5000
B11: Rendimento em Carteira | D11: 0.0089
B12: Sugestão de Investimento (30%) | D12: =D10*30% -> 1500
B15: Investimento Mensal
B16: Quanto Investir por Mês? | D16: 2500
B17: Por Quantos Anos? | D17: 5
B18: Taxa de Rendimento Mensal? | D18: 0.01079
B19: Patrimônio Acumulado? | D19: =FV(Taxa_mensal,qtd_anos*12,Aporte*-1) -> 209442.28
B20: Dividendos Mensais? | D20: =Patrimonio*Rendimento_carteira -> 1864.0363
B22: Cenários | C22: Patrimônio Acumulado | D22: Dividendos
A23: 2 | B23: Quanto em 2 Anos? | C23: =FV($D$18,$A23*12,$D$16*-1) -> 68069.068 | D23: =C23*Rendimento_carteira -> 605.81471
A24: 5 | B24: Quanto em 5 Anos? | C24: =FV($D$18,$A24*12,$D$16*-1) -> 209442.28 | D24: =C24*Rendimento_carteira -> 1864.0363
A25: 10 | B25: Quanto em 10 Anos? | C25: =FV($D$18,$A25*12,$D$16*-1) -> 608210.53 | D25: =C25*Rendimento_carteira -> 5413.0737
A26: 20 | B26: Quanto em 20 Anos? | C26: =FV($D$18,$A26*12,$D$16*-1) -> 2812996 | D26: =C26*Rendimento_carteira -> 25035.664
A27: 30 | B27: Quanto em 30 Anos? | C27: =FV($D$18,$A27*12,$D$16*-1) -> 10805424 | D27: =C27*Rendimento_carteira -> 96168.275
B30: PERFIL | C30: Agressivo
B31: Valor a ser Investido por Mês | C31: =Aporte -> 2500
B33: TIPOS DE FII | C33: Percentual Sugerido | D33: Valores
B34: Papel | C34: =VLOOKUP($C$30&"-"&B34,'Tabela apoio'!$A:$D,4,FALSE) -> 0.5 | D34: =C34*$C$31 -> 1250
B35: Tijolo | C35: =VLOOKUP($C$30&"-"&B35,'Tabela apoio'!$A:$D,4,FALSE) -> 0.1 | D35: =C35*$C$31 -> 250
B36: Hibridos | C36: =VLOOKUP($C$30&"-"&B36,'Tabela apoio'!$A:$D,4,FALSE) -> 0.05 | D36: =C36*$C$31 -> 125
B37: Fofs | C37: =VLOOKUP($C$30&"-"&B37,'Tabela apoio'!$A:$D,4,FALSE) -> 0.05 | D37: =C37*$C$31 -> 125
B38: Desenvolvimento | C38: =VLOOKUP($C$30&"-"&B38,'Tabela apoio'!$A:$D,4,FALSE) -> 0.2 | D38: =C38*$C$31 -> 500
B39: Hotelarias | C39: =VLOOKUP($C$30&"-"&B39,'Tabela apoio'!$A:$D,4,FALSE) -> 0.1 | D39: =C39*$C$31 -> 250
B40: Total | D40: =SUM(D34:D39) -> 2500

Sheet Tabela apoio
A4: Chave | B4: PERFIL | C4: Tipos de Fiis | D4: %
A5: =B5&"-"&C5 -> Conservador-Papel | B5: Conservador | C5: Papel | D5: 0.3
A6: =B6&"-"&C6 -> Conservador-Tijolo | B6: Conservador | C6: Tijolo | D6: 0.5
A7: =B7&"-"&C7 -> Conservador-Hibridos | B7: Conservador | C7: Hibridos | D7: 0.1
A8: =B8&"-"&C8 -> Conservador-Fofs | B8: Conservador | C8: Fofs | D8: 0.1
A9: =B9&"-"&C9 -> Conservador-Desenvolvimento | B9: Conservador | C9: Desenvolvimento | D9: 0
A10: =B10&"-"&C10 -> Conservador-Hotelarias | B10: Conservador | C10: Hotelarias | D10: 0
A11: =B11&"-"&C11 -> Moderado-Papel | B11: Moderado | C11: Papel | D11: 0.32
A12: =B12&"-"&C12 -> Moderado-Tijolo | B12: Moderado | C12: Tijolo | D12: 0.35
A13: =B13&"-"&C13 -> Moderado-Hibridos | B13: Moderado | C13: Hibridos | D13: 0.08
A14: =B14&"-"&C14 -> Moderado-Fofs | B14: Moderado | C14: Fofs | D14: 0.05
A15: =B15&"-"&C15 -> Moderado-Desenvolvimento | B15: Moderado | C15: Desenvolvimento | D15: 0.1
A16: =B16&"-"&C16 -> Moderado-Hotelarias | B16: Moderado | C16: Hotelarias | D16: 0.1
... A22: =B22&"-"&C22 -> Agressivo-Hotelarias | B22: Agressivo | C22: Hotelarias | D22: 0.1
